color_profiles/sRGB_ICC_v4_Appearance.icc
facturix.py
templates/minimum_exemple.xml
templates/minimum_template_fix.xml
templates/minimum_template_without_bt31.xml
templates/minimum_template_without_bt31_bt13.xml
templates/template_MINIMUM.xml
validators/FACTUR-X_MINIMUM.sch
validators/FACTUR-X_MINIMUM.xsd
validators/FACTUR-X_MINIMUM_urn_un_unece_uncefact_data_standard_QualifiedDataType_100.xsd
validators/FACTUR-X_MINIMUM_urn_un_unece_uncefact_data_standard_ReusableAggregateBusinessInformationEntity_100.xsd
validators/FACTUR-X_MINIMUM_urn_un_unece_uncefact_data_standard_UnqualifiedDataType_100.xsd
facturix-1.0.8.dist-info/LICENSE
facturix-1.0.8.dist-info/METADATA
facturix-1.0.8.dist-info/WHEEL
facturix-1.0.8.dist-info/RECORD
