Metadata-Version: 2.1
Name: facturix
Version: 1.0.8
Summary: 
License: GPLv3
Author: Virgile
Author-email: virgile.dauge@pm.me
Requires-Python: >=3.10,<4.0
Classifier: License :: Other/Proprietary License
Classifier: Programming Language :: Python :: 3
Classifier: Programming Language :: Python :: 3.10
Classifier: Programming Language :: Python :: 3.11
Classifier: Programming Language :: Python :: 3.12
Classifier: Programming Language :: Python :: 3.13
Requires-Dist: factur-x (==3.1)
Requires-Dist: lxml (>=5.3.0,<6.0.0)
Requires-Dist: pandas (>=2.2.3,<3.0.0)
Requires-Dist: pypdf (>=5.1.0,<6.0.0)
Requires-Dist: setuptools (>=75.6.0,<76.0.0)
